Workbook

Sheet CLIENT
A1: Mon audit Patrimoine — FICHE CLIENT
A2: Informations personnelles et situation familiale
A4: PRÉNOM PRINCIPAL | B4: Michel
A5: NOM PRINCIPAL | B5: Michu
A6: ÂGE PRINCIPAL | B6: 48
A7: EMAIL
A8: RÉFÉRENCE DOSSIER | B8: mich_mich
A10: SITUATION DU CONJOINT
A11: PRÉNOM CONJOINT | B11: Michel
A12: NOM CONJOINT | B12: Michu
A13: ÂGE CONJOINT | B13: 47
A14: STATUT MARITAL | B14: Marié
A16: ENFANTS À CHARGE
A17: NOMBRE D'ENFANTS | B17: 2
A19: NOM ENFANT | B19: ÂGE | C19: SITUATION | D19: ALLOCATIONS ?
A20: antoine | B20: 22 | C20: etudiant | D20: oui
A21: rose | B21: 17 | C21: lycéenne | D21: non
A24: OBJECTIFS PATRIMONIAUX
A25: Réduire les impôts | B25: X
A26: Préparer la retraite | B26: ☐
A27: Transmettre aux enfants | B27: ☐
A28: Couvrir frais scolarité | B28: ☐

Sheet FISCALITÉ
A1: SITUATION FISCALE 2025
A3: REVENUS BRUTS
A4: Revenu brut global principal (€)
A5: Revenu brut global conjoint (€)
A6: TOTAL revenu brut global (€) | B6: =B4+B5 -> 0
A9: RÉFÉRENCES FISCALES
A10: Revenu fiscal de référence (€)
A11: Parts fiscales
A13: TAUX MARGINAL D'IMPOSITION (TMI)
A14: TMI calculée (%) | B14: =IF(B10<10225,0,IF(B10<26070,0.11,IF(B10<74545,0.3,IF(B10<160336,0.41,0.45)))) -> 0
A17: PLAFOND PER DISPONIBLE
A18: Plafond année N (RBG × 10%) (€) | B18: =MIN(B6*0.1,35194) -> 0
A19: Plafond antérieur non utilisé (€)
A20: TOTAL plafond disponible (€) | B20: =MIN(B18+B19,35194) -> 0

Sheet PATRIMOINE
A1: PATRIMOINE ACTUEL
A3: IMMOBILIER
A4: Résidence principale (€)
A5: Autres biens immobiliers (€)
A6: TOTAL immobilier (€) | B6: =B4+B5 -> 0
A8: LIQUIDITÉS
A9: Livrets / Comptes courants (€)
A10: LDDS / PEL (€)
A11: TOTAL liquidités (€) | B11: =B9+B10 -> 0
A13: ASSURANCE-VIE — CONTRATS EXISTANTS
A14: NOM CONTRAT | B14: VALEUR ACTUELLE (€) | C14: BÉNÉFICIAIRES | D14: DATE D'EFFET
A18: TOTAL assurance-vie (€) | B18: =SUM(B15:B17) -> 0
A20: AUTRES ACTIFS
A21: Actions / Bourse (€)
A22: Autres (€)
A24: PATRIMOINE TOTAL (€) | B24: =B6+B11+B18+B21+B22 -> 0

Sheet RETRAITE
A1: PLANIFICATION RETRAITE
A3: HORIZONS DE RETRAITE
A4: Âge actuel (ans)
A5: Âge retraite visé (ans)
A6: Ans avant retraite | B6: =B5-B4 -> 0
A8: REVENUS ACTUELS vs RETRAITE
A9: Revenu net mensuel actuel (€)
A10: Revenu mensuel souhaité retraite (€)
A12: PROJECTION ÉPARGNE RETRAITE
A13: Épargne retraite actuelle (€)
A14: Rendement annuel attendu (%) | B14: 3.5
A15: Capital retraite projeté (€) | B15: =B13*POWER(1+B14/100,B6) -> 0

Sheet SCENARIO 1
A1: SCÉNARIO 1 — SITUATION ACTUELLE
A3: SIMULATION PER
A4: Versement PER envisagé (€) | B4: 0
A5: Revenu fiscal de référence (€) | B5: =FISCALITÉ!B10 -> 0
A6: TMI (%) | B6: =FISCALITÉ!B14 -> 0
A7: Économie fiscale IR (€) | B7: =B4*B6/100 -> 0
A8: Coût réel du versement (€) | B8: =B4-B7 -> 0

Sheet SCENARIO 2
A1: SCÉNARIO 2 — PER OPTIMAL
A3: SIMULATION PER
A4: Versement PER envisagé (€) | B4: =FISCALITÉ!B20 -> 0
A5: Revenu fiscal de référence (€) | B5: =FISCALITÉ!B10 -> 0
A6: TMI (%) | B6: =FISCALITÉ!B14 -> 0
A7: Économie fiscale IR (€) | B7: =B4*B6/100 -> 0
A8: Coût réel du versement (€) | B8: =B4-B7 -> 0

Sheet SCENARIO 3
A1: SCÉNARIO 3 — PER + AV OPTIMISÉE
A3: SIMULATION PER
A4: Versement PER envisagé (€) | B4: =FISCALITÉ!B20 -> 0
A5: Revenu fiscal de référence (€) | B5: =FISCALITÉ!B10 -> 0
A6: TMI (%) | B6: =FISCALITÉ!B14 -> 0
A7: Économie fiscale IR (€) | B7: =B4*B6/100 -> 0
A8: Coût réel du versement (€) | B8: =B4-B7 -> 0
A10: OPTIMISATION ASSURANCE-VIE
A11: Restructuration recommandée ? | B11: Voir analyse patrimoniale

Sheet SYNTHÈSE
A1: SYNTHÈSE COMPARATIVE DES SCÉNARIOS
B3: SCÉNARIO 1 | C3: SCÉNARIO 2 | D3: SCÉNARIO 3
A4: Versement PER (€) | B4: ='SCENARIO 1'!B3 -> 0 | C4: ='SCENARIO 2'!B3 -> 0 | D4: ='SCENARIO 3'!B3 -> 0
A5: Économie fiscale annuelle (€) | B5: ='SCENARIO 1'!B4 -> 0 | C5: ='SCENARIO 2'!B4 -> 0 | D5: ='SCENARIO 3'!B4 -> 0
A6: Coût réel (€) | B6: ='SCENARIO 1'!B5 -> 0 | C6: ='SCENARIO 2'!B5 -> 0 | D6: ='SCENARIO 3'!B5 -> 0
A7: Capital retraite projeté (€) | B7: ='SCENARIO 1'!B6 -> 0 | C7: ='SCENARIO 2'!B6 -> 0 | D7: ='SCENARIO 3'!B6 -> 0
A10: RECOMMANDATION
A12: ✅ Scénario recommandé :
A13: Scénario 2 (PER optimal) — Meilleur rapport économie/effort

Sheet EXPORT JSON
A1: 🔄 EXPORT DONNÉES POUR HERITUM API
A3: Comment exporter vos données ?
A4: 1. Remplissez complètement tous les onglets ci-dessus
A5: 2. Appuyez sur le bouton 'GÉNÉRER JSON' (sera disponible en version macro)
A6: 3. Copez le JSON généré ci-dessous
A7: 4. Collez-le dans per.mon-audit-patrmoine.fr pour lancer les simulations
A9: ✅ Les données sensibles restent locales — seules les données anonymisées seront envoyées
A11: APERÇU JSON (À GÉNÉRER)
A12: {"client": {"prenom": "[voir CLIENT!B4]", "nom": "[voir CLIENT!B5]", "age": "[voir CLIENT!B6]"}, "fiscalite": {"revenu_brut_global": "[voir FISCALITÉ!B6]", "revenu_fiscal_reference": "[voir FISCALITÉ!B10]", "tmi": "[voir FISCALITÉ!B14]", "plafond_per_disponible": "[voir FISCALITÉ!B20]"}, "patrimoine": {"total": "[voir PATRIMOINE!B24]"}, "scenarios": [{"nom": "Situation actuelle", "versement_per": 0}, {"nom": "PER optimal", "versement_per": "[voir SCENARIO 2!B4]"}, {"nom": "PER + AV optimisée", "versement_per": "[voir SCENARIO 3!B4]"}]}
